nifti2bids/__init__.py
nifti2bids/_constants.py
nifti2bids/_decorators.py
nifti2bids/_exceptions.py
nifti2bids/_helpers.py
nifti2bids/audit.py
nifti2bids/bids.py
nifti2bids/io.py
nifti2bids/logging.py
nifti2bids/metadata.py
nifti2bids/parsers.py
nifti2bids/simulate.py
nifti2bids-0.15.0.dist-info/licenses/LICENSE
nifti2bids-0.15.0.dist-info/METADATA
nifti2bids-0.15.0.dist-info/WHEEL
nifti2bids-0.15.0.dist-info/top_level.txt
nifti2bids-0.15.0.dist-info/RECORD
